addepy/__init__.py
addepy/client.py
addepy/constants.py
addepy/exceptions.py
addepy/resources/__init__.py
addepy/resources/base.py
addepy/resources/admin/__init__.py
addepy/resources/admin/audit.py
addepy/resources/admin/billable_portfolios.py
addepy/resources/admin/client_portal.py
addepy/resources/admin/contacts.py
addepy/resources/admin/files.py
addepy/resources/admin/import_tool.py
addepy/resources/admin/reports.py
addepy/resources/admin/roles.py
addepy/resources/admin/target_allocations.py
addepy/resources/admin/teams.py
addepy/resources/admin/users.py
addepy/resources/admin/view_sets.py
addepy/resources/ownership/__init__.py
addepy/resources/ownership/entities.py
addepy/resources/ownership/external_ids.py
addepy/resources/ownership/groups.py
addepy/resources/ownership/positions.py
addepy/resources/portfolio/__init__.py
addepy/resources/portfolio/analysis.py
addepy/resources/portfolio/arguments.py
addepy/resources/portfolio/attributes.py
addepy/resources/portfolio/benchmarks.py
addepy/resources/portfolio/composite_securities.py
addepy/resources/portfolio/constituent_attributes.py
addepy/resources/portfolio/historical_prices.py
addepy/resources/portfolio/jobs.py
addepy/resources/portfolio/snapshots.py
addepy/resources/portfolio/transaction_jobs.py
addepy/resources/portfolio/transactions.py
addepy-0.3.0.dist-info/LICENSE
addepy-0.3.0.dist-info/METADATA
addepy-0.3.0.dist-info/WHEEL
addepy-0.3.0.dist-info/top_level.txt
addepy-0.3.0.dist-info/RECORD
