Metadata-Version: 2.2
Name: addepy
Version: 0.3.0
Summary: Unofficial Python SDK for the Addepar API
Author-email: Max Sands <maxsands700@email.com>
License: MIT
Project-URL: Homepage, https://github.com/maxsands700/addepy
Project-URL: Repository, https://github.com/maxsands700/addepy
Keywords: addepar,api,sdk,finance,wealth-management
Classifier: Development Status :: 3 - Alpha
Classifier: Intended Audience :: Developers
Classifier: Programming Language :: Python :: 3.10
Classifier: Programming Language :: Python :: 3.11
Classifier: Programming Language :: Python :: 3.12
Classifier: Programming Language :: Python :: 3.13
Requires-Python: >=3.10
License-File: LICENSE
Requires-Dist: requests>=2.25.0
Requires-Dist: python-dotenv>=0.19.0
Requires-Dist: pandas>=1.3.0
Provides-Extra: dev
Requires-Dist: pytest; extra == "dev"
Requires-Dist: pytest-cov; extra == "dev"
Requires-Dist: black; extra == "dev"
Requires-Dist: ruff; extra == "dev"
Requires-Dist: mypy; extra == "dev"
